demo_package_2025/__init__.py
demo_package_2025/calculator.py
demo_package_2025-0.1.dist-info/LICENSE
demo_package_2025-0.1.dist-info/METADATA
demo_package_2025-0.1.dist-info/WHEEL
demo_package_2025-0.1.dist-info/top_level.txt
demo_package_2025-0.1.dist-info/RECORD
