Metadata-Version: 2.2
Name: demo_package_2025
Version: 0.1
Summary: A simple demo package for adding two numbers
Home-page: https://github.com/jaehoon0905/demo_package_2025
Author: Jaehoon Lee
Author-email: 68533989+jaehoon0905@users.noreply.github.com
License: MIT
Keywords: demo package add numbers
Classifier: Programming Language :: Python :: 3
Classifier: Programming Language :: Python :: 3.7
Classifier: Programming Language :: Python :: 3.8
Classifier: Programming Language :: Python :: 3.9
Classifier: License :: OSI Approved :: MIT License
Requires-Python: >=3.7
License-File: LICENSE
Dynamic: author
Dynamic: author-email
Dynamic: classifier
Dynamic: description
Dynamic: description-content-type
Dynamic: home-page
Dynamic: keywords
Dynamic: license
Dynamic: requires-python
Dynamic: summary
